icotest/__init__.py
icotest/cli/commander.py
icotest/cli/tool.py
icotest/config/__init__.py
icotest/config/config.py
icotest/config/config.yaml
icotest/config/user.yaml
icotest/firmware.py
icotest/test/__init__.py
icotest/test/conftest.py
icotest/test/support/common.py
icotest/test/support/node.py
icotest/test/support/sensor_node.py
icotest/test/support/sth.py
icotest/test/test_sensor_node.py
icotest/test/test_sth.py
icotest/test/test_stu.py
icotest-0.7.0.dist-info/METADATA
icotest-0.7.0.dist-info/WHEEL
icotest-0.7.0.dist-info/entry_points.txt
icotest-0.7.0.dist-info/RECORD
