Metadata-Version: 2.4
Name: icotest
Version: 0.7.0
Summary: Hardware tests for ICOtronic system
Keywords: smart-tool,smh,stu,sth,tool-holder
Author: René Schwaiger
Author-email: rene.schwaiger@ift.at
Requires-Python: >=3.12,<4
Classifier: Development Status :: 3 - Alpha
Classifier: Natural Language :: English
Classifier: Operating System :: MacOS
Classifier: Operating System :: POSIX :: Linux
Classifier: Operating System :: Microsoft :: Windows :: Windows 11
Classifier: Programming Language :: Python
Provides-Extra: dev
Requires-Dist: Flake8-pyproject (>=1.2.3) ; extra == "dev"
Requires-Dist: anyio (>=4.11)
Requires-Dist: dynaconf (>=3.1.12,<4)
Requires-Dist: icotronic (>=6.0.1,<=7)
Requires-Dist: mypy (>=1.18.2) ; extra == "dev"
Requires-Dist: platformdirs (>=3.5.0,<5)
Requires-Dist: pydoclint[flake8] (>=0.7.3) ; extra == "dev"
Requires-Dist: pylint (>=3.3.8) ; extra == "dev"
Requires-Dist: pytest (>=9.0.1,<10)
Requires-Dist: pytest-rerunfailures (>=16.1) ; extra == "dev"
Requires-Dist: semantic-version (>=2,<3)
Requires-Dist: sphinx-pyproject (>=0.3) ; extra == "dev"
Requires-Dist: sphinx_rtd_theme ; extra == "dev"
Requires-Dist: universal-startfile (>=0.4)
Project-URL: Source, https://github.com/mytoolit/ICOtest/
